pylandstats/spatiotemporal.py
pylandstats/adjacency.cpython-39-x86_64-linux-gnu.so
pylandstats/__init__.py
pylandstats/multilandscape.py
pylandstats/landscape.py
pylandstats/adjacency.pyx
pylandstats/settings.py
pylandstats/adjacency.c
pylandstats/zonal.py
pylandstats-3.0.3.dist-info/top_level.txt
pylandstats-3.0.3.dist-info/RECORD
pylandstats-3.0.3.dist-info/LICENSE
pylandstats-3.0.3.dist-info/METADATA
pylandstats-3.0.3.dist-info/WHEEL
