Metadata-Version: 2.1
Name: pylandstats
Version: 3.0.3
Summary: Computing landscape metrics in the Python ecosystem.
Author-email: Martí Bosch <marti.bosch@epfl.ch>
License: GPL-3.0
Project-URL: Repository, https://github.com/martibosch/pylandstats
Classifier: License :: OSI Approved :: GNU General Public License v3 (GPLv3)
Classifier: Natural Language :: English
Classifier: Programming Language :: Python :: 3
Classifier: Programming Language :: Python :: 3.9
Classifier: Programming Language :: Python :: 3.10
Classifier: Programming Language :: Python :: 3.11
Classifier: Programming Language :: Python :: 3.12
Classifier: Programming Language :: Python :: 3.13
Requires-Python: >=3.9
License-File: LICENSE
Requires-Dist: dask
Requires-Dist: geopandas
Requires-Dist: matplotlib>=2.2
Requires-Dist: numpy>=1.15
Requires-Dist: pandas>=0.23
Requires-Dist: rasterio>=1.0.0
Requires-Dist: scipy>=1.0.0
Provides-Extra: test
Requires-Dist: coverage[toml]; extra == "test"
Requires-Dist: pytest; extra == "test"
Requires-Dist: pytest-cov; extra == "test"
Requires-Dist: ruff; extra == "test"
Provides-Extra: dev
Requires-Dist: build; extra == "dev"
Requires-Dist: commitizen; extra == "dev"
Requires-Dist: nox; extra == "dev"
Requires-Dist: pre-commit; extra == "dev"
Requires-Dist: pip; extra == "dev"
Requires-Dist: toml; extra == "dev"
Requires-Dist: twine; extra == "dev"
Provides-Extra: doc
Requires-Dist: m2r2; extra == "doc"
Requires-Dist: myst-nb; extra == "doc"
Requires-Dist: pydata-sphinx-theme; extra == "doc"
Requires-Dist: sphinx; extra == "doc"
